README
setup.cfg
setup.py
bin/cool_math
cool_math/__init__.py
cool_math/square.py
cool_math.egg-info/PKG-INFO
cool_math.egg-info/SOURCES.txt
cool_math.egg-info/dependency_links.txt
cool_math.egg-info/requires.txt
cool_math.egg-info/top_level.txt