Metadata-Version: 1.1
Name: cool-math
Version: 1.4
Summary: Cool math
Home-page: https://github.com/missingdays/cool_math
Author: missingdays
Author-email: rebovykin@gmail.com
License: UNKNOWN
Download-URL: https://github.com/missingdays/cool_math/archive/1.4.tar.gz
Keywords: math
Platform: UNKNOWN
